{"is_source_file": true, "format": "JavaScript", "description": "This file configures the testing environment for a JavaScript project using Jest and the Testing Library. It imports custom matchers from '@testing-library/jest-dom' to facilitate assertions on DOM nodes during testing.", "external_files": ["@testing-library/jest-dom"], "external_methods": ["expect.toHaveTextContent", "expect"], "published": [], "classes": [], "methods": [], "calls": ["import '@testing-library/jest-dom'"], "search-terms": ["setupTests.js", "jest-dom", "testing-library", "Jest", "DOM assertions"], "state": 2, "file_id": 4, "knowledge_revision": 20, "git_revision": "9a6c0460e761aac34674c14e665d11d6828faa42", "ctags": [], "hash": "1a77571e1a8cf36018a41bcedf60db75", "format-version": 4, "code-base-name": "tic_tac_toe_frontend", "filename": "tic_tac_toe_frontend/src/setupTests.js", "revision_history": [{"20": "9a6c0460e761aac34674c14e665d11d6828faa42"}]}